demo/Demo.py
demo/GetQuoteDemo.py
demo/TradeDemo.py
demo/__init__.py
demo/utils_redis.py
framework/__init__.py
framework/engine_event.py
framework/log_handler.py
framework/plot_manager.py
framework/quote_manager.py
framework/ring_buffer.py
framework/strategies_manager.py
framework/utils.py
framework/utils_requests.py
strategies_framework-1.3.2.dist-info/LICENSE
strategies_framework-1.3.2.dist-info/METADATA
strategies_framework-1.3.2.dist-info/WHEEL
strategies_framework-1.3.2.dist-info/top_level.txt
strategies_framework-1.3.2.dist-info/zip-safe
strategies_framework-1.3.2.dist-info/RECORD
