Metadata-Version: 2.1
Name: strategies-framework
Version: 1.3.2
Summary: StrategiesFramework
Home-page: https://github.com/StarsAaron
Author: Aaron
Author-email: 103514303@qq.com
License: MIT
Platform: UNKNOWN
Classifier: Programming Language :: Python :: 3
Classifier: License :: OSI Approved :: MIT License
Classifier: Operating System :: OS Independent
Requires-Dist: requests
Requires-Dist: logbook
Requires-Dist: zmq
